[
	{
		"file": "E:\\Repos\\Courses\\ToonTanks\\Source\\ToonTanks\\BasePawn.cpp",
		"arguments": [
			"C:\\Program Files\\Microsoft Visual Studio\\2022\\Community\\VC\\Tools\\MSVC\\14.37.32822\\bin\\Hostx64\\x64\\cl.exe",
			"@E:\\Repos\\Courses\\ToonTanks\\.vscode\\compileCommands_Default\\ToonTanks.1.rsp"
		],
		"directory": "D:\\Games\\Epic Games\\UE_5.3\\Engine\\Source"
	},
	{
		"file": "E:\\Repos\\Courses\\ToonTanks\\Source\\ToonTanks\\BasePawn.h",
		"arguments": [
			"C:\\Program Files\\Microsoft Visual Studio\\2022\\Community\\VC\\Tools\\MSVC\\14.37.32822\\bin\\Hostx64\\x64\\cl.exe",
			"@E:\\Repos\\Courses\\ToonTanks\\.vscode\\compileCommands_Default\\ToonTanks.1.rsp"
		],
		"directory": "D:\\Games\\Epic Games\\UE_5.3\\Engine\\Source"
	},
	{
		"file": "E:\\Repos\\Courses\\ToonTanks\\Source\\ToonTanks\\Tank.cpp",
		"arguments": [
			"C:\\Program Files\\Microsoft Visual Studio\\2022\\Community\\VC\\Tools\\MSVC\\14.37.32822\\bin\\Hostx64\\x64\\cl.exe",
			"@E:\\Repos\\Courses\\ToonTanks\\.vscode\\compileCommands_Default\\ToonTanks.1.rsp"
		],
		"directory": "D:\\Games\\Epic Games\\UE_5.3\\Engine\\Source"
	},
	{
		"file": "E:\\Repos\\Courses\\ToonTanks\\Source\\ToonTanks\\Tank.h",
		"arguments": [
			"C:\\Program Files\\Microsoft Visual Studio\\2022\\Community\\VC\\Tools\\MSVC\\14.37.32822\\bin\\Hostx64\\x64\\cl.exe",
			"@E:\\Repos\\Courses\\ToonTanks\\.vscode\\compileCommands_Default\\ToonTanks.1.rsp"
		],
		"directory": "D:\\Games\\Epic Games\\UE_5.3\\Engine\\Source"
	},
	{
		"file": "E:\\Repos\\Courses\\ToonTanks\\Source\\ToonTanks\\ToonTanks.Build.cs",
		"arguments": [
			"C:\\Program Files\\Microsoft Visual Studio\\2022\\Community\\VC\\Tools\\MSVC\\14.37.32822\\bin\\Hostx64\\x64\\cl.exe",
			"@E:\\Repos\\Courses\\ToonTanks\\.vscode\\compileCommands_Default\\ToonTanks.1.rsp"
		],
		"directory": "D:\\Games\\Epic Games\\UE_5.3\\Engine\\Source"
	},
	{
		"file": "E:\\Repos\\Courses\\ToonTanks\\Source\\ToonTanks\\ToonTanks.cpp",
		"arguments": [
			"C:\\Program Files\\Microsoft Visual Studio\\2022\\Community\\VC\\Tools\\MSVC\\14.37.32822\\bin\\Hostx64\\x64\\cl.exe",
			"@E:\\Repos\\Courses\\ToonTanks\\.vscode\\compileCommands_Default\\ToonTanks.1.rsp"
		],
		"directory": "D:\\Games\\Epic Games\\UE_5.3\\Engine\\Source"
	},
	{
		"file": "E:\\Repos\\Courses\\ToonTanks\\Source\\ToonTanks\\ToonTanks.h",
		"arguments": [
			"C:\\Program Files\\Microsoft Visual Studio\\2022\\Community\\VC\\Tools\\MSVC\\14.37.32822\\bin\\Hostx64\\x64\\cl.exe",
			"@E:\\Repos\\Courses\\ToonTanks\\.vscode\\compileCommands_Default\\ToonTanks.1.rsp"
		],
		"directory": "D:\\Games\\Epic Games\\UE_5.3\\Engine\\Source"
	}
]